gempa_terkini/__init__.py
recent_earthquake_indonesia-0.4.1.dist-info/LICENSE
recent_earthquake_indonesia-0.4.1.dist-info/METADATA
recent_earthquake_indonesia-0.4.1.dist-info/WHEEL
recent_earthquake_indonesia-0.4.1.dist-info/top_level.txt
recent_earthquake_indonesia-0.4.1.dist-info/RECORD
