Metadata-Version: 2.1
Name: recent-earthquake-indonesia
Version: 0.4.1
Summary: This package will get the latest earthquake in Indonesia taken from BMKG
Home-page: https://github.com/Reinz-Stuff/indonesia-recent-earthquake
Author: Fauzi Kurniawan
Author-email: fauzik354313@gmail.com
Project-URL: Github, https://github.com/Reinz-Stuff
Classifier: Programming Language :: Python :: 3
Classifier: License :: OSI Approved :: GNU General Public License v3 (GPLv3)
Classifier: Operating System :: OS Independent
Classifier: Development Status :: 4 - Beta
Requires-Python: >=3.6
License-File: LICENSE
